<?xml version="1.0" encoding="UTF-8" standalone="yes"?>





<item>
<title>-[COLOR  yellow] PORTUGAL [/COLOR]</title>
<link>http://Ignoreme</link>
<thumbnail></thumbnail>
<fanart></fanart>
<externallink>https://raw.githubusercontent.com/lokiyotnt69/Mundodiablo2.0/master/PORTUGAL.xml</externallink>	
</item>




<item>
<title>-[COLOR  blue] USA[/COLOR]</title>
<link>http://Ignoreme</link>
<thumbnail></thumbnail>
<fanart></fanart>
<externallink>https://github.com/lokiyotnt69/Mundodiablo2.0/blob/master/usa.xml</externallink>	
</item>



<item>
<title>-[COLOR  yellow] [/COLOR]</title>
<link>http://Ignoreme</link>
<thumbnail></thumbnail>
<fanart></fanart>
<externallink></externallink>	
</item>



<item>
<title>-[COLOR  red]  [/COLOR]</title>
<link>http://Ignoreme</link>
<thumbnail></thumbnail>
<fanart></fanart>
<externallink></externallink>	
</item>



<item>
<title>-[COLOR  yellow]  [/COLOR]</title>
<link>http://Ignoreme</link>
<thumbnail></thumbnail>
<fanart></fanart>
<externallink></externallink>	
</item>



<item>
<title>-[COLOR  red]  [/COLOR]</title>
<link>http://Ignoreme</link>
<thumbnail></thumbnail>
<fanart></fanart>
<externallink></externallink>	
</item>
