<?xml version="1.0" encoding="UTF-8" standalone="yes"?>



 
                        <item>
                        <title>[COLOR green][COLOR blue]• [/COLOR] #0 HD</title>
                        <fanart></fanart>
                        <thumbnail>http://www.digitaltveurope.net/wp-content/uploads/2016/02/0.png</thumbnail>
                        <link>http://smartiptvspain1.mine.nu:980/live/AdrianDaSilva/Hujh34GGnF/53480.ts</link>
                        </item>
 
 
 
 
 
                        <item>
                        <title>[COLOR green][COLOR blue]• [/COLOR] La 1</title>
                        <fanart></fanart>
                        <thumbnail>http://2.bp.blogspot.com/-6-fKLjM9mCg/UD1cou_ShcI/AAAAAAAABaY/S2sZl05uGt0/s1600/tve.png</thumbnail>
                        <link>http://smartiptvspain1.mine.nu:980/live/AdrianDaSilva/Hujh34GGnF/53499.ts</link>
                        </item>
 
 
 
 
 
 
                        <item>
                        <title>[COLOR green][COLOR blue]• [/COLOR] La 2</title>
                        <fanart></fanart>
                        <thumbnail>https://worktel.co.uk/www/assets/wwwstatic/img/prensa/tve2.png</thumbnail>
                        <link>http://smartiptvspain1.mine.nu:980/live/AdrianDaSilva/Hujh34GGnF/53497.ts</link>
                        </item>
 
 
                        <item>
                        <title>[COLOR green][COLOR blue]• [/COLOR] Antena 3</title>
                        <fanart></fanart>
                        <thumbnail>http://i44.tinypic.com/55pa9j.png</thumbnail>
                        <link>http://smartiptvspain1.mine.nu:980/live/AdrianDaSilva/Hujh34GGnF/53495.ts</link>
                        </item>
 
 
 
 
                        <item>
                        <title>[COLOR green][COLOR blue]• [/COLOR] Cuatro</title>
                        <fanart></fanart>
                        <thumbnail>http://www.mediaset.es/mediasetcom/brand-download/png/cuatro_logo_500.png</thumbnail>
                        <link>http://smartiptvspain1.mine.nu:980/live/AdrianDaSilva/Hujh34GGnF/53493.ts</link>
                        </item>
 
 
                        <item>
                        <title>[COLOR green][COLOR blue]• [/COLOR] Telecinco</title>
                        <fanart></fanart>
                        <thumbnail>http://www.mediaset.es/mediasetcom/brand-download/png/telecinco_logo_500.png</thumbnail>
                        <link>http://smartiptvspain1.mine.nu:980/live/AdrianDaSilva/Hujh34GGnF/53491.ts</link>
                        </item>
 
 
 
 
                        <item>
                        <title>[COLOR green][COLOR blue]• [/COLOR] La Sexta</title>
                        <fanart></fanart>
                        <thumbnail>http://afectadosventaviviendapublica.files.wordpress.com/2014/04/logo-de-la-sextaok.jpg</thumbnail>
                        <link>http://smartiptvspain1.mine.nu:980/live/AdrianDaSilva/Hujh34GGnF/53489.ts</link>
                        </item>
 
 
                         <item>
                        <title>[COLOR green][COLOR blue]• [/COLOR] Cosmo</title>
                        <fanart></fanart>
                        <thumbnail>http://farm6.static.flickr.com/5050/5372194459_2c1ea137ab.jpg</thumbnail>
                        <link>http://smartiptvspain1.mine.nu:980/live/AdrianDaSilva/Hujh34GGnF/53451.ts</link>
                        </item>
 
 
 
 
                        <item>
                        <title>[COLOR green][COLOR blue]• [/COLOR] Divinity</title>
                        <fanart></fanart>
                        <thumbnail>http://www.caratulasylogos.com/sites/default/files/divinity.jpg</thumbnail>
                        <link>http://smartiptvspain1.mine.nu:980/live/AdrianDaSilva/Hujh34GGnF/53484.ts</link>
                        </item>
 
 
                        <item>
                        <title>[COLOR green][COLOR blue]• [/COLOR] Energy</title>
                        <fanart></fanart>
                        <thumbnail>http://www.formulatv.com/images/noticias/22800/22845/2.jpg</thumbnail>
                        <link>http://smartiptvspain1.mine.nu:980/live/AdrianDaSilva/Hujh34GGnF/53485.ts</link>
                        </item>
 
 
 
 
                        <item>
                        <title>[COLOR green][COLOR blue]• [/COLOR] FDF</title>
                        <fanart></fanart>
                        <thumbnail>https://telsonepg.wordpress.com/files/2009/07/fdf.jpg</thumbnail>
                        <link>http://smartiptvspain1.mine.nu:980/live/AdrianDaSilva/Hujh34GGnF/53486.ts</link>
                        </item>
 
 
                        <item>
                        <title>[COLOR green][COLOR blue]• [/COLOR] Mega</title>
                        <fanart></fanart>
                        <thumbnail>http://todotele.com/wp-content/uploads/2015/07/LOGO-MEGA.jpg</thumbnail>
                        <link>http://smartiptvspain1.mine.nu:980/live/AdrianDaSilva/Hujh34GGnF/53487.ts</link>
                        </item>
 
 
 
 
                        <item>
                        <title>[COLOR green][COLOR blue]• [/COLOR] Nova</title>
                        <fanart></fanart>
                        <thumbnail>http://www.formulatv.com/images/noticias/27700/27743/1.jpg</thumbnail>
                        <link>http://smartiptvspain1.mine.nu:980/live/AdrianDaSilva/Hujh34GGnF/53502.ts</link>
                        </item>
 
 
                        <item>
                        <title>[COLOR green][COLOR blue]• [/COLOR] Paramount Chanel</title>
                        <fanart></fanart>
                        <thumbnail>http://www.caratulasylogos.com/sites/default/files/paramount_chanel.jpg</thumbnail>
                        <link>http://smartiptvspain1.mine.nu:980/live/AdrianDaSilva/Hujh34GGnF/53483.ts</link>
                        </item>
 
 
 
                     
 
 
                        <item>
                        <title>[COLOR green][COLOR blue]• [/COLOR] Ten</title>
                        <fanart></fanart>
                        <thumbnail>http://tentv.es/wp-content/uploads/2016/05/ten.png</thumbnail>
                        <link>http://smartiptvspain1.mine.nu:980/live/AdrianDaSilva/Hujh34GGnF/53634.ts</link>
                        </item>
 
 
 
 
                        <item>
                        <title>[COLOR green][COLOR blue]• [/COLOR] De Peliculas</title>
                        <fanart></fanart>
                        <thumbnail>https://upload.wikimedia.org/wikipedia/commons/0/08/De_pelicula_logo.png</thumbnail>
                        <link>http://smartiptvspain1.mine.nu:980/live/AdrianDaSilva/Hujh34GGnF/54208.ts</link>
                        </item>
 
 
                        <item>
                        <title>[COLOR green][COLOR blue]• [/COLOR] Estrenos smartiptv</title>
                        <fanart></fanart>
                        <thumbnail>http://www.smart-iptv.info/img/logo.png</thumbnail>
                        <link>http://smartiptvspain1.mine.nu:980/live/AdrianDaSilva/Hujh34GGnF/54334.ts</link>
                        </item>
 
 
 
 
                        <item>
                        <title>[COLOR green][COLOR blue]• [/COLOR] Movistar Estrenos</title>
                        <fanart></fanart>
                        <thumbnail>http://www.vertelevision.online/wp-content/uploads/2017/07/logoMovistarEstrenos.png</thumbnail>
                        <link>http://smartiptvspain1.mine.nu:980/live/AdrianDaSilva/Hujh34GGnF/53478.ts</link>
                        </item>
 
 
                         <item>
                        <title>[COLOR green][COLOR blue]• [/COLOR] Movistar Accion</title>
                        <fanart></fanart>
                        <thumbnail>https://upload.wikimedia.org/wikipedia/commons/thumb/2/20/Movistar_Acci%C3%B3n.svg/1200px-Movistar_Acci%C3%B3n.svg.png</thumbnail>
                        <link>http://smartiptvspain1.mine.nu:980/live/AdrianDaSilva/Hujh34GGnF/53472.ts</link>
                        </item>
 
 
 
 
                        <item>
                        <title>[COLOR green][COLOR blue]• [/COLOR] Movistar De Cine</title>
                        <fanart></fanart>
                        <thumbnail>https://i.ytimg.com/vi/DbNBZAd9Q88/hqdefault.jpg</thumbnail>
                        <link>http://smartiptvspain1.mine.nu:980/live/AdrianDaSilva/Hujh34GGnF/53477.ts</link>
                        </item>
 
 
                        <item>
                        <title>[COLOR green][COLOR blue]• [/COLOR] Movistar Comedia</title>
                        <fanart></fanart>
                        <thumbnail>http://vercanalestv.com/imagenes/movistar-comedia.jpg</thumbnail>
                        <link>http://smartiptvspain1.mine.nu:980/live/AdrianDaSilva/Hujh34GGnF/53475.ts</link>
                        </item>
 
 
 
 
                        <item>
                        <title>[COLOR green][COLOR blue]• [/COLOR] Movistar Extra</title>
                        <fanart></fanart>
                        <thumbnail>http://www.tv-logo.com/pt-data/uploads/images/logo/canalplus_es_xtra.jpg</thumbnail>
                        <link>http://smartiptvspain1.mine.nu:980/live/AdrianDaSilva/Hujh34GGnF/53460.ts</link>
                        </item>
 
 
                        <item>
                        <title>[COLOR green][COLOR blue]• [/COLOR] Movistar De Cine Epañol</title>
                        <fanart></fanart>
                        <thumbnail>https://upload.wikimedia.org/wikipedia/commons/thumb/b/b7/Movistar_Cine_Espa%C3%B1ol.svg/1200px-Movistar_Cine_Espa%C3%B1ol.svg.png</thumbnail>
                        <link>http://smartiptvspain1.mine.nu:980/live/AdrianDaSilva/Hujh34GGnF/53473.ts</link>
                        </item>
 
 
                       <item>
                        <title>[COLOR green][COLOR blue]• [/COLOR] Xtrm</title>
                        <fanart></fanart>
                        <thumbnail>http://canalxtrm.es/wp-content/themes/canalxtrm/images/xtrm-logo.png</thumbnail>
                        <link>http://smartiptvspain1.mine.nu:980/live/AdrianDaSilva/Hujh34GGnF/53446.ts</link>
                        </item>
 
 
 
 
                        <item>
                        <title>[COLOR green][COLOR blue]• [/COLOR] Amc</title>
                        <fanart></fanart>
                        <thumbnail>http://vignette4.wikia.nocookie.net/logopedia/images/5/50/AMC_2013.png</thumbnail>
                        <link>http://smartiptvspain1.mine.nu:980/live/AdrianDaSilva/Hujh34GGnF/53437.ts</link>
                        </item>
 
 
                        <item>
                        <title>[COLOR green][COLOR blue]• [/COLOR] AXN White</title>
                        <fanart></fanart>
                        <thumbnail>https://upload.wikimedia.org/wikipedia/commons/thumb/6/68/AXN_White_logo_%282015%29.svg/1200px-AXN_White_logo_%282015%29.svg.png</thumbnail>
                        <link>http://smartiptvspain1.mine.nu:980/live/AdrianDaSilva/Hujh34GGnF/53441.ts</link>
                        </item>
 
 
 
 
                        <item>
                        <title>[COLOR green][COLOR blue]• [/COLOR] AXN</title>
                        <fanart></fanart>
                        <thumbnail>https://2.bp.blogspot.com/-Gt2D-M_Odlw/WOlghZ7w_yI/AAAAAAAAE5Y/JJX8Rta6R8oDdjSRoDLe0fW1vhzG7D6UgCLcB/s1600/axn_global_hd_asia.png</thumbnail>
                        <link>http://smartiptvspain1.mine.nu:980/live/AdrianDaSilva/Hujh34GGnF/53439.ts</link>
                        </item>
 
 
                        <item>
                        <title>[COLOR green][COLOR blue]• [/COLOR] A3series</title>
                        <fanart></fanart>
                        <thumbnail>https://imediagala.files.wordpress.com/2015/12/a3series.jpg</thumbnail>
                        <link>http://smartiptvspain1.mine.nu:980/live/AdrianDaSilva/Hujh34GGnF/53482.ts</link>
                        </item>
 
 
 
 
                        <item>
                        <title>[COLOR green][COLOR blue]• [/COLOR] Calle 13</title>
                        <fanart></fanart>
                        <thumbnail>https://upload.wikimedia.org/wikipedia/commons/thumb/2/2c/Calle13_logo.svg/1200px-Calle13_logo.svg.png</thumbnail>
                        <link>http://smartiptvspain1.mine.nu:980/live/AdrianDaSilva/Hujh34GGnF/53443.ts</link>
                        </item>
 
 
                        <item>
                        <title>[COLOR green][COLOR blue]• [/COLOR] Somos</title>
                        <fanart></fanart>
                        <thumbnail>http://adminweb.onlycable.net/img/Canale/small/Somos/Somos_.jpg</thumbnail>
                        <link>http://smartiptvspain1.mine.nu:980/live/AdrianDaSilva/Hujh34GGnF/53447.ts</link>
                        </item>
 
 
 
 
                        <item>
                        <title>[COLOR green][COLOR blue]• [/COLOR] Comedy Central</title>
                        <fanart></fanart>
                        <thumbnail>http://verdirectotv.tv/logos/comedycentral.png</thumbnail>
                        <link>http://smartiptvspain1.mine.nu:980/live/AdrianDaSilva/Hujh34GGnF/53450.ts</link>
                        </item>
 
 
                        <item>
                        <title>[COLOR green][COLOR blue]• [/COLOR] AXN White</title>
                        <fanart></fanart>
                        <thumbnail>https://upload.wikimedia.org/wikipedia/commons/thumb/6/68/AXN_White_logo_%282015%29.svg/1200px-AXN_White_logo_%282015%29.svg.png</thumbnail>
                        <link>http://smartiptvspain1.mine.nu:980/live/AdrianDaSilva/Hujh34GGnF/53441.ts</link>
                        </item>
 
 
 
 
                        <item>
                        <title>[COLOR green][COLOR blue]• [/COLOR] Fox</title>
                        <fanart></fanart>
                        <thumbnail>http://www.paredro.com/wp-content/uploads/2015/02/I0__crtE.png</thumbnail>
                        <link>http://smartiptvspain1.mine.nu:980/live/AdrianDaSilva/Hujh34GGnF/53453.ts</link>
                        </item>
 
 
                        <item>
                        <title>[COLOR green][COLOR blue]• [/COLOR] Fox Life</title>
                        <fanart></fanart>
                        <thumbnail>https://diariodeunatelefila.files.wordpress.com/2014/10/logo-fox-life.png</thumbnail>
                        <link>http://smartiptvspain1.mine.nu:980/live/AdrianDaSilva/Hujh34GGnF/53468.ts</link>
                        </item>
 
 
 
 
                        <item>
                        <title>[COLOR green][COLOR blue]• [/COLOR] Canal Hollywood</title>
                        <fanart></fanart>
                        <thumbnail>https://upload.wikimedia.org/wikipedia/commons/thumb/a/ab/HWD_logo.svg/1200px-HWD_logo.svg.png</thumbnail>
                        <link>http://smartiptvspain1.mine.nu:980/live/AdrianDaSilva/Hujh34GGnF/53470.ts</link>
                        </item>
 
 
                        <item>
                        <title>[COLOR green][COLOR blue]• [/COLOR] Movistar Series</title>
                        <fanart></fanart>
                        <thumbnail>https://upload.wikimedia.org/wikipedia/commons/thumb/d/da/Movistar_Series.svg/1200px-Movistar_Series.svg.png</thumbnail>
                        <link>http://smartiptvspain1.mine.nu:980/live/AdrianDaSilva/Hujh34GGnF/53456.ts</link>
                        </item>
 
 
 
 
                        <item>
                        <title>[COLOR green][COLOR blue]• [/COLOR] Bemad</title>
                        <fanart></fanart>
                        <thumbnail>http://mediasetstatic-a.akamaihd.net/telemania/Logo-Be-Mad_MDSIMA20160421_0484_36.jpg</thumbnail>
                        <link>http://smartiptvspain1.mine.nu:980/live/AdrianDaSilva/Hujh34GGnF/53350.ts</link>
                        </item>
 
 
                        <item>
                        <title>[COLOR green][COLOR blue]• [/COLOR] Series Extra</title>
                        <fanart></fanart>
                        <thumbnail>http://www.movistar.es/estaticos/imagenes/tv-ocio/imagenes/logos-tv/160x130/movistar-series-extra.jpg</thumbnail>
                        <link>http://smartiptvspain1.mine.nu:980/live/AdrianDaSilva/Hujh34GGnF/53459.ts</link>
                        </item>
 
 
 
 
                        <item>
                        <title>[COLOR green][COLOR blue]• [/COLOR] Syfy</title>
                        <fanart></fanart>
                        <thumbnail>https://upload.wikimedia.org/wikipedia/commons/a/ab/Syfylogo.png</thumbnail>
                        <link>http://smartiptvspain1.mine.nu:980/live/AdrianDaSilva/Hujh34GGnF/53461.ts</link>
                        </item>
 
 
                        <item>
                        <title>[COLOR green][COLOR blue]• [/COLOR] TMC</title>
                        <fanart></fanart>
                        <thumbnail>http://www.canaltcm.com/wp-content/uploads/2012/01/TCM_HD_LOGO-programacion.png</thumbnail>
                        <link>http://smartiptvspain1.mine.nu:980/live/AdrianDaSilva/Hujh34GGnF/53463.ts</link>
                        </item>
 
 
 
 
                        <item>
                        <title>[COLOR green][COLOR blue]• [/COLOR] TNT</title>
                        <fanart></fanart>
                        <thumbnail>https://upload.wikimedia.org/wikipedia/commons/thumb/c/c9/TNT_Express_Logo.svg/1200px-TNT_Express_Logo.svg.png</thumbnail>
                        <link>http://smartiptvspain1.mine.nu:980/live/AdrianDaSilva/Hujh34GGnF/53465.ts</link>
                        </item>
 
 
                        <item>
                        <title>[COLOR green][COLOR blue]• [/COLOR] Music Vox TV</title>
                        <fanart></fanart>
                        <thumbnail>http://www.mediafm.net/media/images/original/md5/e/5/e52aa4453577d54df408cb795c0705d4/vox_music_tv.png</thumbnail>
                        <link>http://smartiptvspain1.mine.nu:980/live/AdrianDaSilva/Hujh34GGnF/49825.ts</link>
                        </item>
 
 
                         <item>
                        <title>[COLOR green][COLOR blue]• [/COLOR] MTV Hits</title>
                        <fanart></fanart>
                        <thumbnail>https://upload.wikimedia.org/wikipedia/commons/thumb/f/f1/MTV_HITS_logo.svg/2000px-MTV_HITS_logo.svg.png</thumbnail>
                        <link>http://smartiptvspain1.mine.nu:980/live/AdrianDaSilva/Hujh34GGnF/49822.ts</link>
                        </item>
 
 
 
 
                        <item>
                        <title>[COLOR green][COLOR blue]• [/COLOR] MTV Base</title>
                        <fanart></fanart>
                        <thumbnail>https://pbs.twimg.com/profile_images/799333858550435840/hI76VKKj.jpg</thumbnail>
                        <link>http://smartiptvspain1.mine.nu:980/live/AdrianDaSilva/Hujh34GGnF/49819.ts</link>
                        </item>
 
 
                        <item>
                        <title>[COLOR green][COLOR blue]• [/COLOR] MTV Clasic</title>
                        <fanart></fanart>
                        <thumbnail></thumbnail>
                        <link>http://smartiptvspain1.mine.nu:980/live/AdrianDaSilva/Hujh34GGnF/49820.ts</link>
                        </item>
 
 
 
 
                        <item>
                        <title>[COLOR green][COLOR blue]• [/COLOR] MTV Dance</title>
                        <fanart></fanart>
                        <thumbnail>https://emuzyka-do-pobrania.pl/uploads/teve-kr-ba-sl-img-sl-content-sl-mtv-dance2-kr-gif.jpg</thumbnail>
                        <link>http://smartiptvspain1.mine.nu:980/live/AdrianDaSilva/Hujh34GGnF/49821.ts</link>
                        </item>
 
 
                        <item>
                        <title>[COLOR green][COLOR blue]• [/COLOR] MTV Rock</title>
                        <fanart></fanart>
                        <thumbnail>http://ucretsizmp3.org/wp-content/uploads/2013/12/MTV_ROCKS_logo.svg_.png</thumbnail>
                        <link>http://smartiptvspain1.mine.nu:980/live/AdrianDaSilva/Hujh34GGnF/49824.ts</link>
                        </item>
 
 
 
 
                        <item>
                        <title>[COLOR green][COLOR blue]• [/COLOR] MTV España</title>
                        <fanart></fanart>
                        <thumbnail>http://juventudcalahorra.files.wordpress.com/2011/02/mtv6.jpg</thumbnail>
                        <link>http://smartiptvspain1.mine.nu:980/live/AdrianDaSilva/Hujh34GGnF/53330.ts</link>
                        </item>
 
 
                        <item>
                        <title>[COLOR green][COLOR blue]• [/COLOR] Disney Pixar</title>
                        <fanart></fanart>
                        <thumbnail>https://elbayabuyiba.files.wordpress.com/2015/01/disneypixar_logo.jpg</thumbnail>
                        <link>http://smartiptvspain1.mine.nu:980/live/AdrianDaSilva/Hujh34GGnF/54336.ts</link>
                        </item>
 
 
 
 
                        <item>
                        <title>[COLOR green][COLOR blue]• [/COLOR] Infantiles</title>
                        <fanart></fanart>
                        <thumbnail></thumbnail>
                        <link>http://smartiptvspain1.mine.nu:980/live/AdrianDaSilva/Hujh34GGnF/54331.ts</link>
                        </item>
 
 
                        <item>
                        <title>[COLOR green][COLOR blue]• [/COLOR] Nick Junior</title>
                        <fanart></fanart>
                        <thumbnail>http://media-cache-ec0.pinimg.com/736x/f6/41/78/f64178c861140170995d9928bdf1452d.jpg</thumbnail>
                        <link>http://smartiptvspain1.mine.nu:980/live/AdrianDaSilva/Hujh34GGnF/53343.ts</link>
                        </item>
 
 
                         <item>
                        <title>[COLOR green][COLOR blue]• [/COLOR] Nickelodeon</title>
                        <fanart></fanart>
                        <thumbnail>https://www.recreoviral.com/wp-content/uploads/2015/09/Nickelodeon-lanza-canal-de-caricaturas-de-90%C2%B4s-2.jpg</thumbnail>
                        <link>http://smartiptvspain1.mine.nu:980/live/AdrianDaSilva/Hujh34GGnF/53345.ts</link>
                        </item>
 
 
 
 
                        <item>
                        <title>[COLOR green][COLOR blue]• [/COLOR] Disney Chanel</title>
                        <fanart></fanart>
                        <thumbnail>http://3.bp.blogspot.com/_hQH_YBUEwSI/TFTZB8ldwRI/AAAAAAAAAGI/NvuRRXNhYuU/s1600/LOGO%2BIT%27S%2BON%2BAZUL.png</thumbnail>
                        <link>http://smartiptvspain1.mine.nu:980/live/AdrianDaSilva/Hujh34GGnF/53359.ts</link>
                        </item>
 
 
                        <item>
                        <title>[COLOR green][COLOR blue]• [/COLOR] Disney Junior</title>
                        <fanart></fanart>
                        <thumbnail>http://2.bp.blogspot.com/-_kncJQ5vvL4/TZNtf21dRYI/AAAAAAAAIbQ/e3jzQUrp-CU/w1200-h630-p-k-no-nu/Logo+Disney+Junior.jpg</thumbnail>
                        <link>http://smartiptvspain1.mine.nu:980/live/AdrianDaSilva/Hujh34GGnF/35805.ts</link>
                        </item>
 
 
 
 
                        <item>
                        <title>[COLOR green][COLOR blue]• [/COLOR] Disney XD</title>
                        <fanart></fanart>
                        <thumbnail>http://www.grupocomunica.com/wp-content/uploads/2016/05/Disney-XD-logo.png</thumbnail>
                        <link>http://smartiptvspain1.mine.nu:980/live/AdrianDaSilva/Hujh34GGnF/53341.ts</link>
                        </item>
 
 
                        <item>
                        <title>[COLOR green][COLOR blue]• [/COLOR] Boing</title>
                        <fanart></fanart>
                        <thumbnail>http://www.mediaset.es/mediasetcom/brand-download/png/boing_logo_500_nuevo.png</thumbnail>
                        <link>http://smartiptvspain1.mine.nu:980/live/AdrianDaSilva/Hujh34GGnF/53346.ts</link>
                        </item>
 
 
 
 
                        <item>
                        <title>[COLOR green][COLOR blue]• [/COLOR] Canal Panda</title>
                        <fanart></fanart>
                        <thumbnail>http://portaldascriancas.com/wp-content/uploads/2014/12/Panda-560x360.jpg</thumbnail>
                        <link>http://smartiptvspain1.mine.nu:980/live/AdrianDaSilva/Hujh34GGnF/53338.ts</link>
                        </item>
 
 
                        <item>
                        <title>[COLOR green][COLOR blue]• [/COLOR] Clan TV</title>
                        <fanart></fanart>
                        <thumbnail>http://eslatele.com/wp-content/uploads/blogger/_VCUT9EikwMg/RgMcEZgkLsI/AAAAAAAAAJQ/bOZzinZ8K3Q/s400/clan.jpg</thumbnail>
                        <link>http://smartiptvspain1.mine.nu:980/live/AdrianDaSilva/Hujh34GGnF/53338.ts</link>
                        </item>
 
 
                        <item>
                        <title>[COLOR green][COLOR blue]• [/COLOR] Caza Y Pesca</title>
                        <fanart></fanart>
                        <thumbnail>https://i.ytimg.com/vi/NKnpT16csQQ/maxresdefault.jpg</thumbnail>
                        <link>http://smartiptvspain1.mine.nu:980/live/AdrianDaSilva/Hujh34GGnF/53354.ts</link>
                        </item>
 
 
 
 
 
                        <item>
                        <title>[COLOR green][COLOR blue]• [/COLOR] Historia</title>
                        <fanart></fanart>
                        <thumbnail>http://todotele.com/wp-content/uploads/2016/03/LOGO-CANAL-HISTORIA-MARZO-2016.jpg</thumbnail>
                        <link>http://smartiptvspain1.mine.nu:980/live/AdrianDaSilva/Hujh34GGnF/53365.ts</link>
                        </item>
 
 
 
 
 
 
                        <item>
                        <title>[COLOR green][COLOR blue]• [/COLOR] Iberia</title>
                        <fanart></fanart>
                        <thumbnail>http://www.veotvalameda.es/images/canales/documentales/iberalia.jpg</thumbnail>
                        <link>http://smartiptvspain1.mine.nu:980/live/AdrianDaSilva/Hujh34GGnF/53336.ts</link>
                        </item>
 
 
                        <item>
                        <title>[COLOR green][COLOR blue]• [/COLOR] Odisea</title>
                        <fanart></fanart>
                        <thumbnail>https://telecomkt.files.wordpress.com/2013/01/odisea-hd.jpg</thumbnail>
                        <link>http://smartiptvspain1.mine.nu:980/live/AdrianDaSilva/Hujh34GGnF/53364.ts</link>
                        </item>
 
 
 
 
                        <item>
                        <title>[COLOR green][COLOR blue]• [/COLOR] National Geographic Wild</title>
                        <fanart></fanart>
                        <thumbnail>http://2.bp.blogspot.com/-Vt8Ciwwei5s/Vocga6BhH_I/AAAAAAAAAJE/l2zULvmq16g/s1600/nat-geo-wild-34d22bd9cfeb208abd0e802c83d08489.png</thumbnail>
                        <link>http://smartiptvspain1.mine.nu:980/live/AdrianDaSilva/Hujh34GGnF/53363.ts</link>
                        </item>
 
 
                        <item>
                        <title>[COLOR green][COLOR blue]• [/COLOR] National Geographic</title>
                        <fanart></fanart>
                        <thumbnail>https://s-media-cache-ak0.pinimg.com/originals/bd/0a/43/bd0a4394ef6d6b393aa12ee7b47d5f58.jpg</thumbnail>
                        <link>http://smartiptvspain1.mine.nu:980/live/AdrianDaSilva/Hujh34GGnF/53361.ts</link>
                        </item>
 
 
                        <item>
                        <title>[COLOR green][COLOR blue]• [/COLOR] Documental</title>
                        <fanart></fanart>
                        <thumbnail>https://isakyn.files.wordpress.com/2015/07/docu.jpg</thumbnail>
                        <link>http://smartiptvspain1.mine.nu:980/live/AdrianDaSilva/Hujh34GGnF/53361.ts</link>
                        </item>
 
 
 
 
                        <item>
                        <title>[COLOR green][COLOR blue]• [/COLOR] Viajar</title>
                        <fanart></fanart>
                        <thumbnail>https://pbs.twimg.com/profile_images/469534713023971328/yzb47Vof.png</thumbnail>
                        <link>http://smartiptvspain1.mine.nu:980/live/AdrianDaSilva/Hujh34GGnF/53347.ts</link>
                        </item>
 
 
                         <item>
                        <title>[COLOR green][COLOR blue]• [/COLOR] Aragon TV</title>
                        <fanart></fanart>
                        <thumbnail>http://www.revistalaocaloca.com/wp-content/uploads/aragontvlogo.jpg</thumbnail>
                        <link>http://195.10.10.206/aragontv/hls-live/chunklist.m3u8?GKID=991386747b9e11e785d200163ea2c744</link>
                        </item>
 
 
 
 
                        <item>
                        <title>[COLOR green][COLOR blue]• [/COLOR] TPA</title>
                        <fanart></fanart>
                        <thumbnail>https://upload.wikimedia.org/wikipedia/fr/d/dc/Tpasturias.jpg</thumbnail>
                        <link>http://smartiptvspain1.mine.nu:980/live/AdrianDaSilva/Hujh34GGnF/15500.ts</link>
                        </item>
 
 
                        <item>
                        <title>[COLOR green][COLOR blue]• [/COLOR] Tv Gallega</title>
                        <fanart></fanart>
                        <thumbnail>http://1898.es/wp-content/uploads/2015/03/tvg_logo.png</thumbnail>
                        <link>http://smartiptvspain1.mine.nu:980/live/AdrianDaSilva/Hujh34GGnF/39419.ts</link>
                        </item>


                        <item>
                        <title>[COLOR red][COLOR blue]• [/COLOR] La liga 123</title>
                        <fanart></fanart>
                        <thumbnail></thumbnail>
                        <link>http://smartiptvspain1.mine.nu:980/live/AdrianDaSilva/Hujh34GGnF/54464.ts</link>
                        </item>




                        <item>
                        <title>[COLOR red][COLOR blue]• [/COLOR] Liga 123</title>
                        <fanart></fanart>
                        <thumbnail></thumbnail>
                        <link>http://smartiptvspain1.mine.nu:980/live/AdrianDaSilva/Hujh34GGnF/54463.ts</link>

                        </item>


                        <item>
                        <title>[COLOR red][COLOR blue]• [/COLOR] Bein Sport</title>
                        <fanart></fanart>
                        <thumbnail></thumbnail>
                        <link>http://smartiptvspain1.mine.nu:980/live/AdrianDaSilva/Hujh34GGnF/53401.ts</link>
                        </item>




                        <item>
                        <title>[COLOR red][COLOR blue]• [/COLOR] La Liga</title>
                        <fanart></fanart>
                        <thumbnail></thumbnail>
                        <link>http://smartiptvspain1.mine.nu:980/live/AdrianDaSilva/Hujh34GGnF/53503.ts</link>
                        </item>


                        <item>
                        <title>[COLOR red][COLOR blue]• [/COLOR] Betis TV</title>
                        <fanart></fanart>
                        <thumbnail></thumbnail>
                        <link>http://smartiptvspain1.mine.nu:980/live/AdrianDaSilva/Hujh34GGnF/54350.ts</link>
                        </item>




                        <item>
                        <title>[COLOR red][COLOR blue]• [/COLOR] Formula 1</title>
                        <fanart></fanart>
                        <thumbnail></thumbnail>
                        <link>http://smartiptvspain1.mine.nu:980/live/AdrianDaSilva/Hujh34GGnF/53623.ts</link>
                        </item>


                        <item>
                        <title>[COLOR red][COLOR blue]• [/COLOR] Moto GP</title>
                        <fanart></fanart>
                        <thumbnail></thumbnail>
                        <link>http://smartiptvspain1.mine.nu:980/live/AdrianDaSilva/Hujh34GGnF/53622.ts</link>
                        </item>




                        <item>
                        <title>[COLOR red][COLOR blue]• [/COLOR] Barca TV</title>
                        <fanart></fanart>
                        <thumbnail></thumbnail>
                        <link>http://smartiptvspain1.mine.nu:980/live/AdrianDaSilva/Hujh34GGnF/53368.ts</link>
                        </item>


                         <item>
                        <title>[COLOR red][COLOR blue]• [/COLOR] Bein Liga</title>
                        <fanart></fanart>
                        <thumbnail></thumbnail>
                        <link>http://smartiptvspain1.mine.nu:980/live/AdrianDaSilva/Hujh34GGnF/53388.ts</link>
                        </item>




                        <item>
                        <title>[COLOR red][COLOR blue]• [/COLOR] Bein Sport</title>
                        <fanart></fanart>
                        <thumbnail></thumbnail>
                        <link>http://smartiptvspain1.mine.nu:980/live/AdrianDaSilva/Hujh34GGnF/53401.ts</link>
                        </item>


                        <item>
                        <title>[COLOR red][COLOR blue]• [/COLOR] Bein Sport</title>
                        <fanart></fanart>
                        <thumbnail></thumbnail>
                        <link>http://smartiptvspain1.mine.nu:980/live/AdrianDaSilva/Hujh34GGnF/53400.ts</link>
                        </item>




                        <item>
                        <title>[COLOR red][COLOR blue]• [/COLOR] La Liga</title>
                        <fanart></fanart>
                        <thumbnail></thumbnail>
                        <link>http://smartiptvspain1.mine.nu:980/live/AdrianDaSilva/Hujh34GGnF/53409.ts</link>
                        </item>


                        <item>
                        <title>[COLOR red][COLOR blue]• [/COLOR] La Liga</title>
                        <fanart></fanart>
                        <thumbnail></thumbnail>
                        <link>http://smartiptvspain1.mine.nu:980/live/AdrianDaSilva/Hujh34GGnF/53408.ts</link>
                        </item>




                        <item>
                        <title>[COLOR red][COLOR blue]• [/COLOR] Formula 1</title>
                        <fanart></fanart>
                        <thumbnail></thumbnail>
                        <link>http://smartiptvspain1.mine.nu:980/live/AdrianDaSilva/Hujh34GGnF/53411.ts</link>
                        </item>


                        <item>
                        <title>[COLOR red][COLOR blue]• [/COLOR] Formula 1</title>
                        <fanart></fanart>
                        <thumbnail></thumbnail>
                        <link>http://smartiptvspain1.mine.nu:980/live/AdrianDaSilva/Hujh34GGnF/53410.ts</link>
                        </item>


                        <item>
                        <title>[COLOR red][COLOR blue]• [/COLOR] Movistar Futbol</title>
                        <fanart></fanart>
                        <thumbnail></thumbnail>
                        <link>http://smartiptvspain1.mine.nu:980/live/AdrianDaSilva/Hujh34GGnF/53413.ts</link>
                        </item>




                        <item>
                        <title>[COLOR red][COLOR blue]• [/COLOR] Movistar Futbol</title>
                        <fanart></fanart>
                        <thumbnail></thumbnail>
                        <link>http://smartiptvspain1.mine.nu:980/live/AdrianDaSilva/Hujh34GGnF/53412.ts</link>
                        </item>


                        <item>
                        <title>[COLOR red][COLOR blue]• [/COLOR] Moto Gp</title>
                        <fanart></fanart>
                        <thumbnail></thumbnail>
                        <link>http://smartiptvspain1.mine.nu:980/live/AdrianDaSilva/Hujh34GGnF/53417.ts</link>
                        </item>


                        <item>
                        <title>[COLOR red][COLOR blue]• [/COLOR] Moto GP</title>
                        <fanart></fanart>
                        <thumbnail></thumbnail>
                        <link>http://smartiptvspain1.mine.nu:980/live/AdrianDaSilva/Hujh34GGnF/53416.ts</link>
                        </item>




                        <item>
                        <title>[COLOR red][COLOR blue]• [/COLOR] Bein Liga</title>
                        <fanart></fanart>
                        <thumbnail></thumbnail>
                        <link>http://smartiptvspain1.mine.nu:980/live/AdrianDaSilva/Hujh34GGnF/35605.ts</link>
                        </item>


                       <item>
                        <title>[COLOR red][COLOR blue]• [/COLOR] Partidazo</title>
                        <fanart></fanart>
                        <thumbnail></thumbnail>
                        <link>http://smartiptvspain1.mine.nu:980/live/AdrianDaSilva/Hujh34GGnF/53418.ts</link>
                        </item>


                        <item>
                        <title>[COLOR red][COLOR blue]• [/COLOR] Partidazo</title>
                        <fanart></fanart>
                        <thumbnail></thumbnail>
                        <link>http://smartiptvspain1.mine.nu:980/live/AdrianDaSilva/Hujh34GGnF/54443.ts</link>
                        </item>




                        <item>
                        <title>[COLOR red][COLOR blue]• [/COLOR] Movistar Futbol</title>
                        <fanart></fanart>
                        <thumbnail></thumbnail>
                        <link>http://smartiptvspain1.mine.nu:980/live/AdrianDaSilva/Hujh34GGnF/53412.ts</link>
                        </item>


                        <item>
                        <title>[COLOR red][COLOR blue]• [/COLOR] La Liga</title>
                        <fanart></fanart>
                        <thumbnail></thumbnail>
                        <link>http://smartiptvspain1.mine.nu:980/live/AdrianDaSilva/Hujh34GGnF/35778.ts</link>
                        </item>


                        <item>
                        <title>[COLOR red][COLOR blue]• [/COLOR] Bein La Liga</title>
                        <fanart></fanart>
                        <thumbnail></thumbnail>
                        <link>http://smartiptvspain1.mine.nu:980/live/AdrianDaSilva/Hujh34GGnF/35764.ts</link>
                        </item>




                        <item>
                        <title>[COLOR red][COLOR blue]• [/COLOR] Formula 1</title>
                        <fanart></fanart>
                        <thumbnail></thumbnail>
                        <link>http://smartiptvspain1.mine.nu:980/live/AdrianDaSilva/Hujh34GGnF/35757.ts</link>
                        </item>


                        <item>
                        <title>[COLOR red][COLOR blue]• [/COLOR] Moto GP</title>
                        <fanart></fanart>
                        <thumbnail></thumbnail>
                        <link>http://smartiptvspain1.mine.nu:980/live/AdrianDaSilva/Hujh34GGnF/35759.ts</link>
                        </item>


                        <item>
                        <title>[COLOR red][COLOR blue]• [/COLOR] Moto GP</title>
                        <fanart></fanart>
                        <thumbnail></thumbnail>
                        <link>http://smartiptvspain1.mine.nu:980/live/AdrianDaSilva/Hujh34GGnF/50951.ts</link>
                        </item>




                        <item>
                        <title>[COLOR red][COLOR blue]• [/COLOR] Movistar Futbol</title>
                        <fanart></fanart>
                        <thumbnail></thumbnail>
                        <link>http://smartiptvspain1.mine.nu:980/live/AdrianDaSilva/Hujh34GGnF/50937.ts</link>
                        </item>


                        <item>
                        <title>[COLOR red][COLOR blue]• [/COLOR] Golf</title>
                        <fanart></fanart>
                        <thumbnail></thumbnail>
                        <link>http://smartiptvspain1.mine.nu:980/live/AdrianDaSilva/Hujh34GGnF/53415.ts</link>
                        </item>


                        <item>
                        <title>[COLOR red][COLOR blue]• [/COLOR] Real Madrid</title>
                        <fanart></fanart>
                        <thumbnail></thumbnail>
                        <link>http://smartiptvspain1.mine.nu:980/live/AdrianDaSilva/Hujh34GGnF/53367.ts</link>
                        </item>


                        <item>
                        <title>[COLOR red][COLOR blue]• [/COLOR] Sky Sport2</title>
                        <fanart></fanart>
                        <thumbnail></thumbnail>
                        <link>http://smartiptvspain1.mine.nu:980/live/AdrianDaSilva/Hujh34GGnF/49675.ts</link>
                        </item>




                        <item>
                        <title>[COLOR red][COLOR blue]• [/COLOR] Sky Sports F1</title>
                        <fanart></fanart>
                        <thumbnail></thumbnail>
                        <link>http://smartiptvspain1.mine.nu:980/live/AdrianDaSilva/Hujh34GGnF/36241.ts</link>
                        </item>


                        <item>
                        <title>[COLOR red][COLOR blue]• [/COLOR] Sky Sports Moto GP</title>
                        <fanart></fanart>
                        <thumbnail></thumbnail>
                        <link>http://smartiptvspain1.mine.nu:980/live/AdrianDaSilva/Hujh34GGnF/37305.ts</link>
                        </item>


                        <item>
                        <title>[COLOR red][COLOR blue]• [/COLOR] Teledeporte</title>
                        <fanart></fanart>
                        <thumbnail></thumbnail>
                        <link>http://smartiptvspain1.mine.nu:980/live/AdrianDaSilva/Hujh34GGnF/35818.ts</link>
                        </item>




                        <item>
                        <title>[COLOR red][COLOR blue]• [/COLOR] GolTV</title>
                        <fanart></fanart>
                        <thumbnail></thumbnail>
                        <link>http://smartiptvspain1.mine.nu:980/live/AdrianDaSilva/Hujh34GGnF/53407.ts</link>
                        </item>


                        <item>
                        <title>[COLOR red][COLOR blue]• [/COLOR] Bein Liga</title>
                        <fanart></fanart>
                        <thumbnail></thumbnail>
                        <link>http://smartiptvspain1.mine.nu:980/live/AdrianDaSilva/Hujh34GGnF/35605.ts</link>
                        </item>
						
						