<?xml version="1.0" encoding="UTF-8" standalone="yes"?>




<item>
<title>[COLOR red]* [/COLOR][COLOR blue] ESPERAR [/COLOR][COLOR red] 5 SEGUNDOS  [/COLOR]</title>
<link>http://</link>
</item>







<item>
            <title>[COLOR gold][COLOR orange]**JHG** [/COLOR]MOVISTAR GP[COLOR red][/COLOR]</title>
            <sportsdevil>http://zagaiptv.eklablog.com/moto-gp-p1157318</sportsdevil>
            <referer>http://zagaiptv.eklablog.com/</referer>
            <thumbnail></thumbnail>
            </item>
			
<item>
            <title>[COLOR gold][COLOR orange]*JHG [/COLOR] LA LIGA[COLOR red][/COLOR]</title>
            <sportsdevil>http://verdirectotv.com/tv/deportes2/plusliga.html/</sportsdevil>
            <referer>http://verdirectotv.com/</referer>
            <thumbnail></thumbnail>
            </item>
			
<item>
            <title>[COLOR gold][COLOR orange]*JHG** [/COLOR] FORMULA 1 [COLOR red][/COLOR]</title>
            <sportsdevil>http://cinestrenostv.tv/canales/envivo/formula1.html/</sportsdevil>
            <referer>http://latelete.tv/</referer>
            <thumbnail></thumbnail>
            </item>
			
<item>
            <title>[COLOR gold]BEIN[COLOR orange]**JHG** [/COLOR] LA LIGA[COLOR red][/COLOR]</title>
            <sportsdevil>http://latelete.tv/bein-sports-la-liga-online-en-directo-gratis-24h/</sportsdevil>
            <referer>hhttp://latelete.tv/</referer>
            <thumbnail></thumbnail>
            </item>


			
<item>
            <title>[COLOR gold][COLOR orange]**JHG** [/COLOR]MOVISTAR GP[COLOR red][/COLOR]</title>
            <sportsdevil>http://zagaiptv.eklablog.com/moto-gp-p1157318</sportsdevil>
            <referer>http://zagaiptv.eklablog.com/</referer>
            <thumbnail></thumbnail>
            </item>

			
<item>
            <title>[COLOR gold][COLOR orange]**JHG** [/COLOR] TOROS Tv[COLOR red][/COLOR]</title>
            <sportsdevil>http://zagaiptv.eklablog.com/canal-toros-spain-p1157308</sportsdevil>
            <referer>http://zagaiptv.eklablog.com/</referer>
            <thumbnail></thumbnail>
            </item>
			
<item>
            <title>[COLOR gold][COLOR orange]**JHG** [/COLOR]GOLTV[COLOR red][/COLOR]</title>
            <sportsdevil>http://cinestrenostv.tv/canales/deportes/goltv.php</sportsdevil>
            <referer>http://cinestrenostv.tv/</referer>
            <thumbnail></thumbnail>
            </item>


<item>
            <title>[COLOR gold][COLOR orange]**JHG** [/COLOR]M+ LIGA[COLOR red][/COLOR]</title>
            <sportsdevil>http://tv.b-c-e.us/C_+_Liga.php</sportsdevil>
            <referer>http://tv.b-c-e.us/</referer>
            <thumbnail></thumbnail>
            </item>

<item>
            <title>[COLOR gold] MOVISTAR [COLOR orange]**JHG** [/COLOR]DEPORTES2[COLOR lime][/COLOR]</title>
            <sportsdevil>http://zagaiptv.eklablog.com/canal-deportes-spain-p1157316</sportsdevil>
            <referer>http://zagaiptv.eklablog.com//referer>
            <thumbnail></thumbnail>
            </item>

			
<item>
            <title>[COLOR gold][COLOR orange]**JHG** [/COLOR]MOVISTAR GOLF[COLOR red][/COLOR]</title>
            <sportsdevil>http://cinestrenostv.tv/canales/deportes/plusgolf.php</sportsdevil>
            <referer>http://cinestrenostv.tv/</referer>
            <thumbnail></thumbnail>
            </item>
			
<item>
            <title>[COLOR gold][COLOR orange]**JHG** [/COLOR]MULTIDEPORTES[COLOR red][/COLOR]</title>
            <sportsdevil>http://zagaiptv.eklablog.com/multideportes-p1157518</sportsdevil>
            <referer>http://zagaiptv.eklablog.com/</referer>
            <thumbnail></thumbnail>
            </item>
			
					<item>
            <title>[COLOR gold][COLOR orange]**JHG** [/COLOR]CAZA Y PESCA[COLOR red][/COLOR]</title>
            <sportsdevil>http://zagaiptv.eklablog.com/casa-y-pesca-spain-p1157652</sportsdevil>
            <referer>http://zagaiptv.eklablog.com/</referer>
            <thumbnail></thumbnail>
            </item>
			
<item>
            <title>[COLOR gold][COLOR orange]**JHG** [/COLOR]MOVISTAR DEPORTES 2[COLOR red][/COLOR]</title>
            <sportsdevil>http://zagaiptv.eklablog.com/deportes-2-p1157520</sportsdevil>
            <referer>http://zagaiptv.eklablog.com/</referer>
            <thumbnail></thumbnail>
            </item>
			
<item>
            <title>[COLOR gold][COLOR orange]**JHG** [/COLOR]EUROSPORT 2[COLOR red][/COLOR]</title>
            <sportsdevil>http://zagaiptv.eklablog.com/eurosport2-spain-p1157324</sportsdevil>
            <referer>http://zagaiptv.eklablog.com/</referer>
            <thumbnail></thumbnail>
            </item>